gemini_client-1.0.0.dist-info/licenses/LICENSE
openapi_client/__init__.py
openapi_client/api_client.py
openapi_client/api_response.py
openapi_client/configuration.py
openapi_client/exceptions.py
openapi_client/py.typed
openapi_client/rest.py
openapi_client/api/__init__.py
openapi_client/api/generative_service_api.py
openapi_client/models/__init__.py
openapi_client/models/attribution_source_id.py
openapi_client/models/attribution_source_id_grounding_passage_id.py
openapi_client/models/attribution_source_id_semantic_retriever_chunk.py
openapi_client/models/batch_embed_contents_request.py
openapi_client/models/batch_embed_contents_response.py
openapi_client/models/blob.py
openapi_client/models/candidate.py
openapi_client/models/citation_metadata.py
openapi_client/models/citation_source.py
openapi_client/models/code_execution_result.py
openapi_client/models/condition.py
openapi_client/models/content.py
openapi_client/models/content_embedding.py
openapi_client/models/count_tokens_request.py
openapi_client/models/count_tokens_response.py
openapi_client/models/dynamic_retrieval_config.py
openapi_client/models/embed_content_request.py
openapi_client/models/embed_content_response.py
openapi_client/models/executable_code.py
openapi_client/models/file_data.py
openapi_client/models/function_call.py
openapi_client/models/function_calling_config.py
openapi_client/models/function_declaration.py
openapi_client/models/function_response.py
openapi_client/models/generate_answer_request.py
openapi_client/models/generate_answer_response.py
openapi_client/models/generate_answer_response_input_feedback.py
openapi_client/models/generate_content_request.py
openapi_client/models/generate_content_response.py
openapi_client/models/generate_content_response_prompt_feedback.py
openapi_client/models/generate_content_response_usage_metadata.py
openapi_client/models/generation_config.py
openapi_client/models/google_protobuf_any.py
openapi_client/models/google_search_retrieval.py
openapi_client/models/grounding_attribution.py
gemini_client-1.0.0.dist-info/METADATA
gemini_client-1.0.0.dist-info/WHEEL
gemini_client-1.0.0.dist-info/top_level.txt
gemini_client-1.0.0.dist-info/RECORD
