Metadata-Version: 2.4
Name: gemini-client
Version: 1.0.0
Summary: Python client library for Google Gemini AI API - GenerativeService API
Home-page: https://github.com/AbQaadir/gemini-client
Author: Qaadir
Author-email: Qaadir <qaadireng@gmail.com>
License-Expression: MIT
Project-URL: Repository, https://github.com/AbQaadir/gemini-client
Project-URL: Homepage, https://github.com/AbQaadir/gemini-client
Project-URL: Issues, https://github.com/AbQaadir/gemini-client/issues
Keywords: Gemini,AI,Google,GenerativeAI,OpenAI,Chatbot,LLM
Requires-Python: >= 3.9
License-File: LICENSE
Requires-Dist: urllib3<3.0.0,>=2.1.0
Requires-Dist: python-dateutil>=2.8.2
Requires-Dist: pydantic>=2
Requires-Dist: typing-extensions>=4.7.1
Dynamic: author
Dynamic: home-page
Dynamic: license-file
Dynamic: requires-python
